easytello/__init__.py
easytello/stats.py
easytello/tello.py
easytello-0.0.7.dist-info/LICENSE
easytello-0.0.7.dist-info/METADATA
easytello-0.0.7.dist-info/WHEEL
easytello-0.0.7.dist-info/top_level.txt
easytello-0.0.7.dist-info/RECORD
